langkit/PII_entities.json
langkit/__init__.py
langkit/all_metrics.py
langkit/callback_handler.py
langkit/config/__init__.py
langkit/config/environment.py
langkit/count_regexes.py
langkit/docs/faq.md
langkit/docs/features/quality.md
langkit/docs/features/relevance.md
langkit/docs/features/security.md
langkit/docs/features/sentiment.md
langkit/docs/modules.md
langkit/examples/Batch_to_Whylabs.ipynb
langkit/examples/ChatGPT_Behavioral_Monitoring.ipynb
langkit/examples/Choosing_an_LLM.ipynb
langkit/examples/Custom_Encoder.ipynb
langkit/examples/Detecting_Jailbreaks_and_Prompt_Injections.ipynb
langkit/examples/Detecting_PII_with_Presidio.ipynb
langkit/examples/Injections.ipynb
langkit/examples/Intro_to_Langkit.ipynb
langkit/examples/LLM_to_WhyLabs.ipynb
langkit/examples/LangKit_Config.ipynb
langkit/examples/Langchain_OpenAI_LLM_Monitoring_with_WhyLabs.ipynb
langkit/examples/Local_Models.ipynb
langkit/examples/Logging_Text.ipynb
langkit/examples/Proactive_Injection_Detection.ipynb
langkit/examples/Response_Consistency.ipynb
langkit/examples/Sentiment_and_Toxicity.ipynb
langkit/examples/Toxicity_Model_Configuration.ipynb
langkit/examples/huggingface_langkit_whylabs.ipynb
langkit/examples/tutorials/Safeguarding_and_Monitoring_LLMs.ipynb
langkit/examples/tutorials/Safeguarding_and_Monitoring_LLMs_with_OpenAI.ipynb
langkit/examples/tutorials/Segmented_Validation_Example.ipynb
langkit/examples/tutorials/images/dashboard.png
langkit/examples/tutorials/images/safeguards_pipeline.png
langkit/extract.py
langkit/injections.py
langkit/input_output.py
langkit/light_metrics.py
langkit/llm_metrics.py
langkit/metadata.py
langkit/nlp_scores.py
langkit/openai/__init__.py
langkit/openai/openai.py
langkit/openai_wrapper.py
langkit/pattern_groups.json
langkit/pattern_loader.py
langkit/pii.py
langkit/proactive_injection_detection.py
langkit/regexes.py
langkit/response_hallucination.py
langkit/sentiment.py
langkit/tests/__init__.py
langkit/tests/conftest.py
langkit-0.0.35.dist-info/LICENSE
langkit-0.0.35.dist-info/METADATA
langkit-0.0.35.dist-info/WHEEL
langkit-0.0.35.dist-info/RECORD
