Metadata-Version: 2.1
Name: langkit
Version: 0.0.35
Summary: A language toolkit for monitoring LLM interactions
Home-page: https://docs.whylabs.ai/docs/large-language-model-monitoring
License: Apache-2.0
Author: WhyLabs.ai
Author-email: langkit@whylabs.ai
Requires-Python: >=3.8,<4
Classifier: License :: OSI Approved :: Apache Software License
Classifier: Programming Language :: Python :: 3
Classifier: Programming Language :: Python :: 3.8
Classifier: Programming Language :: Python :: 3.9
Classifier: Programming Language :: Python :: 3.10
Classifier: Programming Language :: Python :: 3.11
Provides-Extra: all
Requires-Dist: datasets (>=2.12.0,<3.0.0) ; extra == "all"
Requires-Dist: detoxify (>=0.5.2,<0.6.0) ; extra == "all"
Requires-Dist: evaluate (>=0.4.0,<0.5.0) ; extra == "all"
Requires-Dist: h5py (>=3.10.0,<4.0.0) ; extra == "all"
Requires-Dist: ipywidgets (>=8.1.1,<9.0.0) ; extra == "all"
Requires-Dist: nltk (>=3.8.1,<4.0.0) ; extra == "all"
Requires-Dist: numpy ; extra == "all"
Requires-Dist: openai (>=0.27.6,<2.0.0) ; extra == "all"
Requires-Dist: pandas
Requires-Dist: presidio-analyzer (>=2.2.351,<3.0.0) ; extra == "all"
Requires-Dist: sentence-transformers (>=2.2.2,<3.0.0) ; extra == "all"
Requires-Dist: torch ; extra == "all"
Requires-Dist: vadersentiment (>=3.3.2,<4.0.0) ; extra == "all"
Requires-Dist: whylabs-textstat (>=0.7.4,<0.8.0)
Requires-Dist: whylogs (>=1.5.0,<2.0.0)
Requires-Dist: xformers ; python_full_version >= "3.8.0" and python_version < "4" and sys_platform == "!macos"
